xtractmime/__init__.py
xtractmime/_patterns.py
xtractmime/_utils.py
xtractmime/mimegroups.py
xtractmime-0.2.1.dist-info/LICENSE
xtractmime-0.2.1.dist-info/METADATA
xtractmime-0.2.1.dist-info/WHEEL
xtractmime-0.2.1.dist-info/top_level.txt
xtractmime-0.2.1.dist-info/RECORD
